httpdis/__init__.py
httpdis/config.py
httpdis/httpdis.py
httpdis/ext/__init__.py
httpdis/ext/httpdis_json.py
httpdis-0.6.26.dist-info/LICENSE
httpdis-0.6.26.dist-info/METADATA
httpdis-0.6.26.dist-info/WHEEL
httpdis-0.6.26.dist-info/top_level.txt
httpdis-0.6.26.dist-info/RECORD
