Metadata-Version: 2.1
Name: httpdis
Version: 0.6.26
Summary: httpdis
Home-page: https://github.com/decryptus/httpdis
Author: Adrien Delle Cave
Author-email: pypi@doowan.net
License: License GPL-3
Platform: UNKNOWN
Classifier: License :: OSI Approved :: GNU General Public License v3 (GPLv3)
Classifier: Natural Language :: English
Classifier: Operating System :: Unix
Classifier: Programming Language :: Python
Classifier: Programming Language :: Python :: 2
Classifier: Programming Language :: Python :: 2.7
Classifier: Programming Language :: Python :: 3
Classifier: Programming Language :: Python :: 3.5
Classifier: Programming Language :: Python :: 3.6
Classifier: Programming Language :: Python :: 3.7
Classifier: Topic :: Internet :: WWW/HTTP :: HTTP Servers
Requires-Python: >=2.7, !=3.0.*, !=3.1.*, !=3.2.*, !=3.3.*, !=3.4.*
Requires-Dist: LEPL
Requires-Dist: python-magic
Requires-Dist: sonicprobe (>=0.3.49)
Requires-Dist: six (>=1.13.0)
Requires-Dist: rfc6266 ; python_version < "3.4"
Requires-Dist: rfc6266-parser ; python_version < "3.6"
Requires-Dist: uc-rfc6266-parser ; python_version >= "3.6"
